pysetup/__init__.py
pysetup/command.py
pysetup/help_text.py
pysetup/main.py
pysetup/setup_text.py
pysetup-2019.6.1.dist-info/LICENSE
pysetup-2019.6.1.dist-info/METADATA
pysetup-2019.6.1.dist-info/WHEEL
pysetup-2019.6.1.dist-info/entry_points.txt
pysetup-2019.6.1.dist-info/top_level.txt
pysetup-2019.6.1.dist-info/RECORD
