Metadata-Version: 2.1
Name: pysetup
Version: 2019.6.1
Summary: Pypi upload tool.
Home-page: https://github.com/Czw96/PySetup
Author: Czw_96
Author-email: 459749926@qq.com
License: UNKNOWN
Platform: UNKNOWN
Classifier: Programming Language :: Python :: 3
Classifier: License :: OSI Approved :: MIT License
Classifier: Operating System :: OS Independent
Requires-Dist: setuptools
Requires-Dist: wheel
Requires-Dist: twine
Requires-Dist: pip
